luckyseven/__init__.py
luckyseven/luckyseven.py
luckyseven-0.0.3.dist-info/LICENSE
luckyseven-0.0.3.dist-info/METADATA
luckyseven-0.0.3.dist-info/WHEEL
luckyseven-0.0.3.dist-info/top_level.txt
luckyseven-0.0.3.dist-info/RECORD
